asyncio_gcloud_ml_engine-0.1.2.dist-info/LICENSE.txt
asyncio_gcloud_ml_engine-0.1.2.dist-info/METADATA
asyncio_gcloud_ml_engine-0.1.2.dist-info/RECORD
asyncio_gcloud_ml_engine-0.1.2.dist-info/WHEEL
asyncio_gcloud_ml_engine-0.1.2.dist-info/top_level.txt
asyncio_ml_engine/__init__.py
asyncio_ml_engine/__version__.py
asyncio_ml_engine/client.py
asyncio_ml_engine/scopes.py
