Metadata-Version: 2.1
Name: asyncio-gcloud-ml-engine
Version: 0.1.2
Summary: An implementation of Google Cloud ML Engine Prediction using aiohttp.
Home-page: https://github.com/brunoalano/asyncio-gcloud-ml-engine
Author: Bruno Alano
Author-email: bruno@neurologic.com.br
License: MIT
Platform: UNKNOWN
Classifier: Programming Language :: Python :: 3
Classifier: License :: OSI Approved :: MIT License
Classifier: Operating System :: OS Independent
Requires-Python: >=3.4
Requires-Dist: aiohttp
Requires-Dist: gcloud-aio-auth
